clvm_rs/__init__.py
clvm_rs/at.py
clvm_rs/casts.py
clvm_rs/chia_dialect.py
clvm_rs/clvm_rs.abi3.so
clvm_rs/clvm_rs.pyi
clvm_rs/clvm_storage.py
clvm_rs/clvm_tree.py
clvm_rs/curry_and_treehash.py
clvm_rs/de.py
clvm_rs/eval_error.py
clvm_rs/program.py
clvm_rs/py.typed
clvm_rs/replace.py
clvm_rs/ser.py
clvm_rs/tree_hash.py
clvm_rs-0.16.3.dist-info/METADATA
clvm_rs-0.16.3.dist-info/WHEEL
clvm_rs.libs/libcrypto-bdaed0ea.so.1.1
clvm_rs-0.16.3.dist-info/RECORD
